cocktaildbpy/__init__.py
cocktaildbpy/constants.py
cocktaildbpy/drink.py
cocktaildbpy/utils.py
cocktaildbpy-0.0.3.dist-info/LICENSE
cocktaildbpy-0.0.3.dist-info/METADATA
cocktaildbpy-0.0.3.dist-info/WHEEL
cocktaildbpy-0.0.3.dist-info/top_level.txt
cocktaildbpy-0.0.3.dist-info/RECORD
