Metadata-Version: 2.1
Name: cocktaildbpy
Version: 0.0.3
Summary: A small python library to interact with cocktaildb api (https://www.thecocktaildb.com/api.php)
Author-email: OSS Student Teacher <ossstudenthelper@proton.me>
Project-URL: Homepage, https://github.com/ossstudenthelper/cocktaildbpy
Project-URL: Bug Tracker, https://github.com/ossstudenthelper/cocktaildbpy/issues
Classifier: Programming Language :: Python :: 3
Classifier: License :: OSI Approved :: MIT License
Classifier: Operating System :: OS Independent
Requires-Python: >=3.7
License-File: LICENSE
Requires-Dist: requests
Requires-Dist: dataclasses ; python_version < "3.7"
